{"request":{"args":{"page":"index","text":"Суды","sll":"44.680171999999985,43.01867800002452","sspn":"1.0848999023437322,0.16951489115989204","source":"catalog","results":"1000","key":"y7607cd50083c207c0886816ab11cd085","output":"json"},"argArrays":{"page":["index"],"text":["Суды"],"sll":["44.680171999999985,43.01867800002452"],"sspn":["1.0848999023437322,0.16951489115989204"],"source":["catalog"],"results":["1000"],"key":["y7607cd50083c207c0886816ab11cd085"],"output":["json"]}},"title":"Суды","map":{"bounds":[[44.20564597,43.01016097],[44.75151624,43.06012441]]},"vpage":{"name":"serp","data":{"mode":"bizfinder","reqid":"140756247869958628","serpid":"140756247869958628","businesses":{"request":{"experimental_test-ids":"","experimental_alternative_verticals":"1","direct":"page:131","dump":false,"experimental_distinguish_layers":"1","experimental_extended_global_search":"1","experimental_maxadv":"200","experimental_tld":"ru","geocoder_geometry":"1","geocoder_sco":"latlong","geocoder_pin":"0","lang":"ru_RU","origin":"maps-catalog","results":1000,"skip":0,"snippets":"router/1.x,panoramas/1.x,masstransit/1.x,business/1.x,businessrating/1.x,photos/1.x","source":"catalog","test_buckets":"","type":"biz,geo,psearch,web","yabs":"page:144","yandex_gid":"39","text":"Суды","ll":"44.680171999999985,43.01867800002452","spn":"1.0848999023437322,0.16951489115989204"},"GeoObjectCollection":{"type":"FeatureCollection","properties":{"Attribution":{"Sources":{"yandex":{"id":"yandex","authors":[{"name":"Яндекс","uri":"http://www.yandex.ru"}]},"sm":{"id":"sm","authors":[{"name":"Желтые страницы Юга России","uri":"http://sam5.ru"}]}}},"ResponseMetaData":{"SearchRequest":{"request":"Суды","results":1000,"skip":0,"boundedBy":[[44.13772436,42.93386506],[45.22261972,43.10337274]]},"SearchResponse":{"found":23,"Sort":{"type":"rank"},"Point":{"type":"Point","coordinates":[44.47858111,43.03514781]},"boundedBy":[[44.20564597,43.01016097],[44.75151624,43.06012441]],"SourceMetaDataList":{"SourceMetaData":{"ResponseMetaData":{"BusinessSearchRequest":{"request":"суды","results":500,"boundedBy":[[44.137724,42.933865],[45.22262,43.103373]]},"BusinessSearchResponse":{"sort":"rank","found":16,"Categories":[{"name":"Суды","InternalCategoryInfo":{"AppleData":{"acid":"publicservicesgovt","level":"1"}}}],"Filters":[{"id":"open_now","type":"Boolean","name":"работает сейчас"}],"Point":{"type":"Point","coordinates":[44.478581,43.040446]},"boundedBy":[[44.207002,43.021749],[44.75016,43.059136]]}}}},"InternalResponseInfo":{"display":"multiple","context":"BgAAAAEA0tNH4A9XRkBIoWsKZIJFQLD///+/W/E/AL7b+KmyxT8AAAAAyAAAAAAAAAAAAAAAAAAAAAANKwAAAQA=","reqid":"140756247869958628","serpid":"140756247869958628"}}}},"features":[{"type":"Feature","properties":{"CompanyMetaData":{"id":"1019314965","name":"Арбитражный Суд","address":"Владикавказ, пл. Свободы, 5","postalCode":"362038","AddressDetails":{"Country":{"AddressLine":"Владикавказ, пл. Свободы, 5","CountryNameCode":"RU","CountryName":"Россия","AdministrativeArea":{"AdministrativeAreaName":"Республика Северная Осетия - Алания","Locality":{"LocalityName":"Владикавказ город","Thoroughfare":{"ThoroughfareName":"Свободы площадь","Premise":{"PremiseNumber":"5","PostalCode":{"PostalCodeNumber":"362038"}}}}}}},"Categories":[{"name":"Суды","nameHighlight":[[0,4]],"InternalCategoryInfo":{"AppleData":{"acid":"publicservicesgovt","level":"1"}}}],"Phones":[{"type":"phone","formatted":"+7 (8672) 53-71-17","country":"7","prefix":"8672","number":"537117"},{"type":"fax","formatted":"+7 (8672) 53-28-44","country":"7","prefix":"8672","number":"532844"}],"Hours":{"Availabilities":[{"Monday":true,"Tuesday":true,"Wednesday":true,"Thursday":true,"Friday":true,"Intervals":[{"from":"09:00:00","to":"13:00:00"},{"from":"14:00:00","to":"18:00:00"}]}],"text":"пн-пт 09:00-18:00, перерыв 13:00-14:00"},"Geo":{"precision":"exact"},"InternalCompanyInfo":{"ids":["1019314965","1007171511"],"geoid":"33"}},"Router":{"types":["auto"]},"BusinessRating":{"ratings":0,"reviews":0},"description":"Владикавказ, пл. Свободы, 5","name":"Арбитражный Суд","boundedBy":[[44.67232076,43.01873054],[44.6887779,43.03080501]],"attributions":["#yandex"]},"geometry":{"type":"Point","coordinates":[44.680549,43.024768]}},{"type":"Feature","properties":{"CompanyMetaData":{"id":"1028567762","name":"Конституционный Суд","address":"Владикавказ, пл. Свободы, 1","postalCode":"362038","AddressDetails":{"Country":{"AddressLine":"Владикавказ, пл. Свободы, 1","CountryNameCode":"RU","CountryName":"Россия","AdministrativeArea":{"AdministrativeAreaName":"Республика Северная Осетия - Алания","Locality":{"LocalityName":"Владикавказ город","Thoroughfare":{"ThoroughfareName":"Свободы площадь","Premise":{"PremiseNumber":"1","PostalCode":{"PostalCodeNumber":"362038"}}}}}}},"Categories":[{"name":"Суды","nameHighlight":[[0,4]],"InternalCategoryInfo":{"AppleData":{"acid":"publicservicesgovt","level":"1"}}}],"Phones":[{"type":"phone","formatted":"+7 (8672) 53-27-98","country":"7","prefix":"8672","number":"532798"},{"type":"phone","formatted":"+7 (8672) 53-58-32","country":"7","prefix":"8672","number":"535832"},{"type":"fax","formatted":"+7 (8672) 53-79-05","country":"7","prefix":"8672","number":"537905"}],"Hours":{"Availabilities":[{"Monday":true,"Tuesday":true,"Wednesday":true,"Thursday":true,"Friday":true,"Intervals":[{"from":"09:00:00","to":"13:00:00"},{"from":"14:00:00","to":"18:00:00"}]}],"text":"пн-пт 09:00-18:00, перерыв 13:00-14:00"},"Geo":{"precision":"exact"},"InternalCompanyInfo":{"ids":["1028567762"],"geoid":"33"}},"Router":{"types":["auto"]},"BusinessRating":{"ratings":0,"reviews":0},"description":"Владикавказ, пл. Свободы, 1","name":"Конституционный Суд","boundedBy":[[44.6744318,43.01849325],[44.69088894,43.03056777]],"attributions":["#yandex"]},"geometry":{"type":"Point","coordinates":[44.68266,43.024531]}},{"type":"Feature","properties":{"CompanyMetaData":{"id":"1003294931","name":"Советский районный суд","address":"Владикавказ, ул. Московская, 4","postalCode":"362031","AddressDetails":{"Country":{"AddressLine":"Владикавказ, ул. Московская, 4","CountryNameCode":"RU","CountryName":"Россия","AdministrativeArea":{"AdministrativeAreaName":"Республика Северная Осетия - Алания","Locality":{"LocalityName":"город Владикавказ","Thoroughfare":{"ThoroughfareName":"улица Московская","Premise":{"PremiseNumber":"4","PostalCode":{"PostalCodeNumber":"362031"}}}}}}},"Categories":[{"name":"Суды","nameHighlight":[[0,4]],"InternalCategoryInfo":{"AppleData":{"acid":"publicservicesgovt","level":"1"}}}],"Phones":[{"type":"phone","formatted":"+7 (8672) 24-05-71","country":"7","prefix":"8672","number":"240571"},{"type":"phone","formatted":"+7 (8672) 24-06-10","country":"7","prefix":"8672","number":"240610"},{"type":"fax","formatted":"+7 (8672) 24-04-85","country":"7","prefix":"8672","number":"240485"}],"Hours":{"Availabilities":[{"Monday":true,"Tuesday":true,"Wednesday":true,"Thursday":true,"Friday":true,"Intervals":[{"from":"09:00:00","to":"13:00:00"},{"from":"14:00:00","to":"18:00:00"}]}],"text":"пн-пт 09:00-18:00, перерыв 13:00-14:00"},"Geo":{"precision":"exact"},"InternalCompanyInfo":{"ids":["1003294931"],"geoid":"33"}},"Router":{"types":["auto"]},"BusinessRating":{"ratings":0,"reviews":0},"description":"Владикавказ, ул. Московская, 4","name":"Советский районный суд","boundedBy":[[44.64310755,43.05308904],[44.65956469,43.06515671]],"attributions":["#yandex"]},"geometry":{"type":"Point","coordinates":[44.651336,43.059123]}},{"type":"Feature","properties":{"CompanyMetaData":{"id":"1238474605","name":"Владикавказкий гарнизонный военный суд","address":"Владикавказ, просп. Коста, 166","AddressDetails":{"Country":{"AddressLine":"Владикавказ, просп. Коста, 166","CountryNameCode":"RU","CountryName":"Россия","AdministrativeArea":{"AdministrativeAreaName":"Республика Северная Осетия - Алания","Locality":{"LocalityName":"город Владикавказ","Thoroughfare":{"ThoroughfareName":"проспект Коста","Premise":{"PremiseNumber":"166"}}}}}},"Categories":[{"name":"Суды","nameHighlight":[[0,4]],"InternalCategoryInfo":{"AppleData":{"acid":"publicservicesgovt","level":"1"}}}],"Phones":[{"type":"phone","formatted":"+7 (8672) 75-21-52","country":"7","prefix":"8672","number":"752152"}],"Hours":{"Availabilities":[{"Monday":true,"Tuesday":true,"Wednesday":true,"Thursday":true,"Friday":true,"Intervals":[{"from":"09:00:00","to":"13:00:00"},{"from":"14:00:00","to":"18:00:00"}]}],"text":"пн-пт 09:00-18:00, перерыв 13:00-14:00"},"Geo":{"precision":"exact"},"InternalCompanyInfo":{"ids":["1238474605"],"geoid":"33"}},"Router":{"types":["auto"]},"BusinessRating":{"ratings":0,"reviews":0},"description":"Владикавказ, просп. Коста, 166","name":"Владикавказкий гарнизонный военный суд","boundedBy":[[44.66050792,43.02319284],[44.67696505,43.03526643]],"attributions":["#yandex"]},"geometry":{"type":"Point","coordinates":[44.668736,43.02923]}},{"type":"Feature","properties":{"CompanyMetaData":{"id":"1074310399","name":"Суд Промышленного района г. Владикавказ","address":"Владикавказ, ул. Зортова, 2","postalCode":"362002","AddressDetails":{"Country":{"AddressLine":"Владикавказ, ул. Зортова, 2","CountryNameCode":"RU","CountryName":"Россия","AdministrativeArea":{"AdministrativeAreaName":"Республика Северная Осетия - Алания","Locality":{"LocalityName":"Владикавказ город","Thoroughfare":{"ThoroughfareName":"Зортова улица","Premise":{"PremiseNumber":"2","PostalCode":{"PostalCodeNumber":"362002"}}}}}}},"Categories":[{"name":"Суды","nameHighlight":[[0,4]],"InternalCategoryInfo":{"AppleData":{"acid":"publicservicesgovt","level":"1"}}}],"Phones":[{"type":"phone","formatted":"+7 (8672) 76-21-21","country":"7","prefix":"8672","number":"762121"},{"type":"fax","formatted":"+7 (8672) 76-62-45","country":"7","prefix":"8672","number":"766245"},{"type":"fax","formatted":"+7 (8672) 76-11-82","country":"7","prefix":"8672","number":"761182"}],"Hours":{"Availabilities":[{"Monday":true,"Tuesday":true,"Wednesday":true,"Thursday":true,"Friday":true,"Intervals":[{"from":"09:00:00","to":"13:00:00"},{"from":"14:00:00","to":"18:00:00"}]}],"text":"пн-пт 09:00-18:00, перерыв 13:00-14:00"},"Geo":{"precision":"exact"},"InternalCompanyInfo":{"ids":["1074310399"],"geoid":"33"}},"Router":{"types":["auto"]},"BusinessRating":{"ratings":0,"reviews":0},"description":"Владикавказ, ул. Зортова, 2","name":"Суд Промышленного района г. Владикавказ","boundedBy":[[44.66322083,43.03304565],[44.67967797,43.04511728]],"attributions":["#yandex"]},"geometry":{"type":"Point","coordinates":[44.671449,43.039082]}},{"type":"Feature","properties":{"CompanyMetaData":{"id":"1074015669","name":"Служба Судебных Приставов Левобережного района","address":"Владикавказ, ул. Зортова, 4","postalCode":"362002","AddressDetails":{"Country":{"AddressLine":"Владикавказ, ул. Зортова, 4","CountryNameCode":"RU","CountryName":"Россия","AdministrativeArea":{"AdministrativeAreaName":"Республика Северная Осетия - Алания","Locality":{"LocalityName":"Владикавказ город","Thoroughfare":{"ThoroughfareName":"Зортова улица","Premise":{"PremiseNumber":"4","PostalCode":{"PostalCodeNumber":"362002"}}}}}}},"Categories":[{"name":"Суды","nameHighlight":[[0,4]],"InternalCategoryInfo":{"AppleData":{"acid":"publicservicesgovt","level":"1"}}}],"Phones":[{"type":"phone","formatted":"+7 (8672) 76-85-77","country":"7","prefix":"8672","number":"768577"},{"type":"fax","formatted":"+7 (8672) 76-11-85","country":"7","prefix":"8672","number":"761185"}],"Hours":{"Availabilities":[{"Monday":true,"Tuesday":true,"Wednesday":true,"Thursday":true,"Friday":true,"Saturday":true,"Intervals":[{"from":"09:00:00","to":"13:00:00"},{"from":"14:00:00","to":"18:00:00"}]}],"text":"пн-сб 09:00-18:00, перерыв 13:00-14:00"},"Geo":{"precision":"exact"},"InternalCompanyInfo":{"ids":["1074015669"],"geoid":"33"}},"Router":{"types":["auto"]},"BusinessRating":{"ratings":0,"reviews":0},"description":"Владикавказ, ул. Зортова, 4","name":"Служба Судебных Приставов Левобережного района","boundedBy":[[44.66179251,43.03531914],[44.67824964,43.04739033]],"attributions":["#yandex"]},"geometry":{"type":"Point","coordinates":[44.670021,43.041355]}},{"type":"Feature","properties":{"CompanyMetaData":{"id":"1077386593","name":"Мировой Судья Судебного Участка № 2, ФГУ","address":"Республика Северная Осетия - Алания, Алагирский р-н, Алагир г., ул. Комсомольская, 28","postalCode":"363240","AddressDetails":{"Country":{"AddressLine":"Республика Северная Осетия - Алания, Алагирский р-н, Алагир г., ул. Комсомольская, 28","CountryNameCode":"RU","CountryName":"Россия","AdministrativeArea":{"AdministrativeAreaName":"Республика Северная Осетия - Алания","SubAdministrativeArea":{"SubAdministrativeAreaName":"Алагирский район","Locality":{"LocalityName":"город Алагир","Thoroughfare":{"ThoroughfareName":"улица Комсомольская","Premise":{"PremiseNumber":"28","PostalCode":{"PostalCodeNumber":"363240"}}}}}}}},"Categories":[{"name":"Суды","nameHighlight":[[0,4]],"InternalCategoryInfo":{"AppleData":{"acid":"publicservicesgovt","level":"1"}}}],"Phones":[{"type":"phone","formatted":"+7 (86731) 2-12-69","country":"7","prefix":"86731","number":"21269"}],"Hours":{"Availabilities":[{"Monday":true,"Tuesday":true,"Wednesday":true,"Thursday":true,"Friday":true,"Intervals":[{"from":"09:00:00","to":"13:00:00"},{"from":"14:00:00","to":"18:00:00"}]}],"text":"пн-пт 09:00-18:00, перерыв 13:00-14:00"},"Geo":{"precision":"exact"},"InternalCompanyInfo":{"ids":["1077386593"],"geoid":"20591"}},"Router":{"types":["auto"]},"BusinessRating":{"ratings":0,"reviews":0},"description":"Республика Северная Осетия - Алания, Алагирский р-н, Алагир г., ул. Комсомольская, 28","name":"Мировой Судья Судебного Участка № 2, ФГУ","boundedBy":[[44.21230249,43.03379031],[44.22875963,43.04586179]],"attributions":["#sm","#yandex"]},"geometry":{"type":"Point","coordinates":[44.220531,43.039826]}},{"type":"Feature","properties":{"CompanyMetaData":{"id":"1068964961","name":"Мировой Судья Судебного Участка № 25","address":"Владикавказ, ул. Московская, 4","postalCode":"362031","AddressDetails":{"Country":{"AddressLine":"Владикавказ, ул. Московская, 4","CountryNameCode":"RU","CountryName":"Россия","AdministrativeArea":{"AdministrativeAreaName":"Республика Северная Осетия - Алания","Locality":{"LocalityName":"город Владикавказ","Thoroughfare":{"ThoroughfareName":"улица Московская","Premise":{"PremiseNumber":"4","PostalCode":{"PostalCodeNumber":"362031"}}}}}}},"Categories":[{"name":"Суды","nameHighlight":[[0,4]],"InternalCategoryInfo":{"AppleData":{"acid":"publicservicesgovt","level":"1"}}}],"Phones":[{"type":"phone","formatted":"+7 (8672) 74-40-09","country":"7","prefix":"8672","number":"744009"}],"Hours":{"Availabilities":[{"Monday":true,"Tuesday":true,"Wednesday":true,"Thursday":true,"Intervals":[{"from":"09:00:00","to":"13:00:00"},{"from":"14:00:00","to":"18:00:00"}]},{"Friday":true,"Intervals":[{"from":"09:00:00","to":"13:00:00"},{"from":"14:00:00","to":"16:45:00"}]}],"text":"пн-чт 09:00-18:00, перерыв 13:00-14:00; пт 09:00-16:45, перерыв 13:00-14:00"},"Geo":{"precision":"exact"},"InternalCompanyInfo":{"ids":["1068964961","1000190592","1028557370","1128818364","1082779797","1066414564","1006154254","1004788078","1098447930"],"geoid":"33"}},"Router":{"types":["auto"]},"BusinessRating":{"ratings":0,"reviews":0},"description":"Владикавказ, ул. Московская, 4","name":"Мировой Судья Судебного Участка № 25","boundedBy":[[44.64310755,43.05308904],[44.65956469,43.06515671]],"attributions":["#yandex"]},"geometry":{"type":"Point","coordinates":[44.651336,43.059123]}},{"type":"Feature","properties":{"CompanyMetaData":{"id":"1056219504","name":"Аппарат Мировых Судей РСО-Алания","address":"Владикавказ, ул. Чкалова, 6","postalCode":"362002","AddressDetails":{"Country":{"AddressLine":"Владикавказ, ул. Чкалова, 6","CountryNameCode":"RU","CountryName":"Россия","AdministrativeArea":{"AdministrativeAreaName":"Республика Северная Осетия - Алания","Locality":{"LocalityName":"Владикавказ город","Thoroughfare":{"ThoroughfareName":"Чкалова улица","Premise":{"PremiseNumber":"6","PostalCode":{"PostalCodeNumber":"362002"}}}}}}},"Categories":[{"name":"Суды","nameHighlight":[[0,4]],"InternalCategoryInfo":{"AppleData":{"acid":"publicservicesgovt","level":"1"}}}],"Phones":[{"type":"phone","formatted":"+7 (8672) 76-84-60","country":"7","prefix":"8672","number":"768460"},{"type":"phone","formatted":"+7 (8672) 51-91-30","country":"7","prefix":"8672","number":"519130"},{"type":"fax","formatted":"+7 (8672) 51-91-25","country":"7","prefix":"8672","number":"519125"}],"Hours":{"Availabilities":[{"Monday":true,"Tuesday":true,"Wednesday":true,"Thursday":true,"Friday":true,"Intervals":[{"from":"09:00:00","to":"13:00:00"},{"from":"14:00:00","to":"18:00:00"}]}],"text":"пн-пт 09:00-18:00, перерыв 13:00-14:00"},"Geo":{"precision":"exact"},"InternalCompanyInfo":{"ids":["1056219504"],"geoid":"33"}},"Router":{"types":["auto"]},"BusinessRating":{"ratings":0,"reviews":0},"description":"Владикавказ, ул. Чкалова, 6","name":"Аппарат Мировых Судей РСО-Алания","boundedBy":[[44.66271777,43.03475901],[44.67917491,43.04683031]],"attributions":["#yandex"]},"geometry":{"type":"Point","coordinates":[44.670946,43.040795]}},{"type":"Feature","properties":{"CompanyMetaData":{"id":"1085540590","name":"Суд, Районный, ФГУ","address":"Республика Северная Осетия - Алания, Алагирский р-н, Алагир г., ул. Терешковой, 4","postalCode":"363240","AddressDetails":{"Country":{"AddressLine":"Республика Северная Осетия - Алания, Алагирский р-н, Алагир г., ул. Терешковой, 4","CountryNameCode":"RU","CountryName":"Россия","AdministrativeArea":{"AdministrativeAreaName":"Республика Северная Осетия - Алания","SubAdministrativeArea":{"SubAdministrativeAreaName":"Алагирский район","Locality":{"LocalityName":"Алагир город","Thoroughfare":{"ThoroughfareName":"Терешковой улица","Premise":{"PremiseNumber":"4","PostalCode":{"PostalCodeNumber":"363240"}}}}}}}},"url":"http://alagirsky.wlk.sudrf.ru","urls":["http://alagirsky.wlk.sudrf.ru"],"Categories":[{"name":"Суды","nameHighlight":[[0,4]],"InternalCategoryInfo":{"AppleData":{"acid":"publicservicesgovt","level":"1"}}}],"Phones":[{"type":"phone","formatted":"+7 (86731) 2-27-14","country":"7","prefix":"86731","number":"22714"},{"type":"phone","formatted":"+7 (86731) 2-02-38","country":"7","prefix":"86731","number":"20238"},{"type":"phone","formatted":"+7 (86731) 3-27-13","country":"7","prefix":"86731","number":"32713"},{"type":"fax","formatted":"+7 (86731) 3-10-40","country":"7","prefix":"86731","number":"31040"}],"Hours":{"Availabilities":[{"Monday":true,"Tuesday":true,"Wednesday":true,"Thursday":true,"Friday":true,"Intervals":[{"from":"09:00:00","to":"13:00:00"},{"from":"14:00:00","to":"18:00:00"}]}],"text":"пн-пт 09:00-18:00, перерыв 13:00-14:00"},"Geo":{"precision":"street"},"InternalCompanyInfo":{"ids":["1085540590"],"geoid":"20591"}},"Router":{"types":["auto"]},"BusinessRating":{"ratings":0,"reviews":0},"description":"Республика Северная Осетия - Алания, Алагирский р-н, Алагир г., ул. Терешковой, 4","name":"Суд, Районный, ФГУ","boundedBy":[[44.19833369,43.03595175],[44.21568914,43.036558]],"attributions":["#sm","#yandex"]},"geometry":{"type":"Point","coordinates":[44.207011,43.036255]}},{"type":"Feature","properties":{"CompanyMetaData":{"id":"1134731717","name":"Суд, Районный, ФГУ","address":"Республика Северная Осетия - Алания, Пригородный р-н, Октябрьское с., ул. Тедеева, 103","postalCode":"363130","AddressDetails":{"Country":{"AddressLine":"Республика Северная Осетия - Алания, Пригородный р-н, Октябрьское с., ул. Тедеева, 103","CountryNameCode":"RU","CountryName":"Россия","AdministrativeArea":{"AdministrativeAreaName":"Республика Северная Осетия - Алания","SubAdministrativeArea":{"SubAdministrativeAreaName":"Пригородный район","Locality":{"LocalityName":"село Октябрьское","Thoroughfare":{"ThoroughfareName":"улица Тедеева","Premise":{"PremiseNumber":"103","PostalCode":{"PostalCodeNumber":"363130"}}}}}}}},"Categories":[{"name":"Суды","nameHighlight":[[0,4]],"InternalCategoryInfo":{"AppleData":{"acid":"publicservicesgovt","level":"1"}}}],"Phones":[{"type":"phone","formatted":"+7 (86738) 2-27-82","country":"7","prefix":"86738","number":"22782"},{"type":"fax","formatted":"+7 (86738) 2-18-66","country":"7","prefix":"86738","number":"21866"}],"Hours":{"Availabilities":[{"Monday":true,"Tuesday":true,"Wednesday":true,"Thursday":true,"Friday":true,"Intervals":[{"from":"09:00:00","to":"13:00:00"},{"from":"14:00:00","to":"18:00:00"}]}],"text":"пн-пт 09:00-18:00, перерыв 13:00-14:00"},"Geo":{"precision":"near"},"InternalCompanyInfo":{"ids":["1134731717","1071312727","1011298774","1120645047","1126796510","1085686165","1058012845","1124583333","1079602299","1003761193","1097584400"],"geoid":"100576"}},"Router":{"types":["auto"]},"BusinessRating":{"ratings":0,"reviews":0},"description":"Республика Северная Осетия - Алания, Пригородный р-н, Октябрьское с., ул. Тедеева, 103","name":"Суд, Районный, ФГУ","boundedBy":[[44.7369276,43.04961058],[44.75338474,43.06167894]],"attributions":["#sm","#yandex"]},"geometry":{"type":"Point","coordinates":[44.745156,43.055645]}},{"type":"Feature","properties":{"CompanyMetaData":{"id":"1023373071","name":"Мировой Судья Судебного Участка № 32, ФГУ","address":"Республика Северная Осетия - Алания, Пригородный р-н, Октябрьское с., ул. Тедеева, 105","postalCode":"363130","AddressDetails":{"Country":{"AddressLine":"Республика Северная Осетия - Алания, Пригородный р-н, Октябрьское с., ул. Тедеева, 105","CountryNameCode":"RU","CountryName":"Россия","AdministrativeArea":{"AdministrativeAreaName":"Республика Северная Осетия - Алания","SubAdministrativeArea":{"SubAdministrativeAreaName":"Пригородный район","Locality":{"LocalityName":"село Октябрьское","Thoroughfare":{"ThoroughfareName":"улица Тедеева","Premise":{"PremiseNumber":"105","PostalCode":{"PostalCodeNumber":"363130"}}}}}}}},"Categories":[{"name":"Суды","nameHighlight":[[0,4]],"InternalCategoryInfo":{"AppleData":{"acid":"publicservicesgovt","level":"1"}}}],"Phones":[{"type":"phone","formatted":"+7 (8672) 44-53-69","country":"7","prefix":"8672","number":"445369"}],"Hours":{"Availabilities":[{"Monday":true,"Tuesday":true,"Wednesday":true,"Thursday":true,"Friday":true,"Intervals":[{"from":"09:00:00","to":"13:00:00"},{"from":"14:00:00","to":"18:00:00"}]}],"text":"пн-пт 09:00-18:00, перерыв 13:00-14:00"},"Geo":{"precision":"near"},"InternalCompanyInfo":{"ids":["1023373071","1028966308","1132425017","1021827239","1108934900","1059269802","1093408988","1134506792","1060455555","1102408405","1064987982","1116471155"],"geoid":"100576"}},"Router":{"types":["auto"]},"BusinessRating":{"ratings":0,"reviews":0},"description":"Республика Северная Осетия - Алания, Пригородный р-н, Октябрьское с., ул. Тедеева, 105","name":"Мировой Судья Судебного Участка № 32, ФГУ","boundedBy":[[44.7369276,43.04961058],[44.75338474,43.06167894]],"attributions":["#sm","#yandex"]},"geometry":{"type":"Point","coordinates":[44.745156,43.055645]}},{"type":"Feature","properties":{"CompanyMetaData":{"id":"1108590548","name":"Мировой Судья Судебного Участка № 15, ФГУ","address":"Республика Северная Осетия - Алания, Пригородный р-н, Октябрьское с., ул. Тедеева, 137","postalCode":"363130","AddressDetails":{"Country":{"AddressLine":"Республика Северная Осетия - Алания, Пригородный р-н, Октябрьское с., ул. Тедеева, 137","CountryNameCode":"RU","CountryName":"Россия","AdministrativeArea":{"AdministrativeAreaName":"Республика Северная Осетия - Алания","SubAdministrativeArea":{"SubAdministrativeAreaName":"Пригородный район","Locality":{"LocalityName":"село Октябрьское","Thoroughfare":{"ThoroughfareName":"улица Тедеева","Premise":{"PremiseNumber":"137","PostalCode":{"PostalCodeNumber":"363130"}}}}}}}},"Categories":[{"name":"Суды","nameHighlight":[[0,4]],"InternalCategoryInfo":{"AppleData":{"acid":"publicservicesgovt","level":"1"}}}],"Phones":[{"type":"phone","formatted":"+7 (8672) 44-35-73","country":"7","prefix":"8672","number":"443573"}],"Hours":{"Availabilities":[{"Monday":true,"Tuesday":true,"Wednesday":true,"Thursday":true,"Friday":true,"Intervals":[{"from":"09:00:00","to":"13:00:00"},{"from":"14:00:00","to":"18:00:00"}]}],"text":"пн-пт 09:00-18:00, перерыв 13:00-14:00"},"Geo":{"precision":"near"},"InternalCompanyInfo":{"ids":["1108590548","1090827482","1051555969","1014968327","1072185719","1077247457","1122618282","1014556690","1037583289","1087808728","1016712781","1039342823","1104099518"],"geoid":"100576"}},"Router":{"types":["auto"]},"BusinessRating":{"ratings":0,"reviews":0},"description":"Республика Северная Осетия - Алания, Пригородный р-н, Октябрьское с., ул. Тедеева, 137","name":"Мировой Судья Судебного Участка № 15, ФГУ","boundedBy":[[44.74191325,43.0499927],[44.75837039,43.06206097]],"attributions":["#sm","#yandex"]},"geometry":{"type":"Point","coordinates":[44.750142,43.056027]}},{"type":"Feature","properties":{"CompanyMetaData":{"id":"1052992200","name":"Мировой Судья Судебного Участка № 20 Промышленного МО","address":"Владикавказ, ул. Цаликова, 24","postalCode":"362011","AddressDetails":{"Country":{"AddressLine":"Владикавказ, ул. Цаликова, 24","CountryNameCode":"RU","CountryName":"Россия","AdministrativeArea":{"AdministrativeAreaName":"Республика Северная Осетия - Алания","Locality":{"LocalityName":"город Владикавказ","Thoroughfare":{"ThoroughfareName":"улица Цаликова","Premise":{"PremiseNumber":"24","PostalCode":{"PostalCodeNumber":"362011"}}}}}}},"Categories":[{"name":"Суды","nameHighlight":[[0,4]],"InternalCategoryInfo":{"AppleData":{"acid":"publicservicesgovt","level":"1"}}}],"Phones":[{"type":"phone","formatted":"+7 (8672) 76-96-01","country":"7","prefix":"8672","number":"769601"}],"Hours":{"Availabilities":[{"Monday":true,"Tuesday":true,"Wednesday":true,"Thursday":true,"Friday":true,"Intervals":[{"from":"09:00:00","to":"13:00:00"},{"from":"14:00:00","to":"18:00:00"}]}],"text":"пн-пт 09:00-18:00, перерыв 13:00-14:00"},"Geo":{"precision":"near"},"InternalCompanyInfo":{"ids":["1052992200"],"geoid":"33"}},"Router":{"types":["auto"]},"BusinessRating":{"ratings":0,"reviews":0},"description":"Владикавказ, ул. Цаликова, 24","name":"Мировой Судья Судебного Участка № 20 Промышленного МО","boundedBy":[[44.66506238,43.04744962],[44.68151951,43.0595184]],"attributions":["#yandex"]},"geometry":{"type":"Point","coordinates":[44.673291,43.053484]}},{"type":"Feature","properties":{"CompanyMetaData":{"id":"1041061885","name":"Мировой Судья Судебного Участка № 21 Промышленного МО","address":"Владикавказ, ул. Цаликова, 24","postalCode":"362011","AddressDetails":{"Country":{"AddressLine":"Владикавказ, ул. Цаликова, 24","CountryNameCode":"RU","CountryName":"Россия","AdministrativeArea":{"AdministrativeAreaName":"Республика Северная Осетия - Алания","Locality":{"LocalityName":"город Владикавказ","Thoroughfare":{"ThoroughfareName":"улица Цаликова","Premise":{"PremiseNumber":"24","PostalCode":{"PostalCodeNumber":"362011"}}}}}}},"Categories":[{"name":"Суды","nameHighlight":[[0,4]],"InternalCategoryInfo":{"AppleData":{"acid":"publicservicesgovt","level":"1"}}}],"Phones":[{"type":"phone","formatted":"+7 (8672) 76-14-12","country":"7","prefix":"8672","number":"761412"}],"Hours":{"Availabilities":[{"Monday":true,"Tuesday":true,"Wednesday":true,"Thursday":true,"Friday":true,"Intervals":[{"from":"09:00:00","to":"13:00:00"},{"from":"14:00:00","to":"18:00:00"}]}],"text":"пн-пт 09:00-18:00, перерыв 13:00-14:00"},"Geo":{"precision":"near"},"InternalCompanyInfo":{"ids":["1041061885"],"geoid":"33"}},"Router":{"types":["auto"]},"BusinessRating":{"ratings":0,"reviews":0},"description":"Владикавказ, ул. Цаликова, 24","name":"Мировой Судья Судебного Участка № 21 Промышленного МО","boundedBy":[[44.66506238,43.04744962],[44.68151951,43.0595184]],"attributions":["#yandex"]},"geometry":{"type":"Point","coordinates":[44.673291,43.053484]}},{"type":"Feature","properties":{"CompanyMetaData":{"id":"1018950189","name":"Мировой Судья Судебного Участка № 22 Промышленного МО","address":"Владикавказ, ул. Цаликова, 24","postalCode":"362011","AddressDetails":{"Country":{"AddressLine":"Владикавказ, ул. Цаликова, 24","CountryNameCode":"RU","CountryName":"Россия","AdministrativeArea":{"AdministrativeAreaName":"Республика Северная Осетия - Алания","Locality":{"LocalityName":"Владикавказ город","Thoroughfare":{"ThoroughfareName":"Цаликова улица","Premise":{"PremiseNumber":"24","PostalCode":{"PostalCodeNumber":"362011"}}}}}}},"Categories":[{"name":"Суды","nameHighlight":[[0,4]],"InternalCategoryInfo":{"AppleData":{"acid":"publicservicesgovt","level":"1"}}}],"Phones":[{"type":"phone","formatted":"+7 (8672) 76-19-89","country":"7","prefix":"8672","number":"761989"}],"Hours":{"Availabilities":[{"Monday":true,"Tuesday":true,"Wednesday":true,"Thursday":true,"Friday":true,"Intervals":[{"from":"09:00:00","to":"13:00:00"},{"from":"14:00:00","to":"18:00:00"}]}],"text":"пн-пт 09:00-18:00, перерыв 13:00-14:00"},"Geo":{"precision":"near"},"InternalCompanyInfo":{"ids":["1018950189"],"geoid":"33"}},"Router":{"types":["auto"]},"BusinessRating":{"ratings":0,"reviews":0},"description":"Владикавказ, ул. Цаликова, 24","name":"Мировой Судья Судебного Участка № 22 Промышленного МО","boundedBy":[[44.66506238,43.04744962],[44.68151951,43.0595184]],"attributions":["#yandex"]},"geometry":{"type":"Point","coordinates":[44.673291,43.053484]}},{"type":"Feature","properties":{"PSearchObjectMetaData":{"id":"7738455","name":"Верховный суд РСО-Алания","nameHighlight":[[10,13]],"kind":"house","Address":{"locality":"Владикавказ (Дзæуджыхъæу)","thoroughfare":"улица Некрасова","premiseNumber":"3"},"address":"Владикавказ (Дзæуджыхъæу), улица Некрасова, 3","category":"суд","categoryHighlight":[[0,3]],"internal":{"category_id":"poi-gov-court","category_name":"суд"}},"Router":{"types":["auto"]},"description":"Владикавказ (Дзæуджыхъæу), улица Некрасова, 3","name":"Верховный суд РСО-Алания","boundedBy":[[44.67941745,43.03115429],[44.67966898,43.0314179]]},"geometry":{"type":"Point","coordinates":[44.679543,43.031286]}},{"type":"Feature","properties":{"PSearchObjectMetaData":{"id":"4246241","name":"Промышленный районный суд","nameHighlight":[[22,25]],"kind":"house","Address":{"locality":"Владикавказ (Дзæуджыхъæу)","thoroughfare":"улица Зортова","premiseNumber":"2"},"address":"Владикавказ (Дзæуджыхъæу), улица Зортова, 2","category":"суд","categoryHighlight":[[0,3]],"internal":{"category_id":"poi-gov-court","category_name":"суд"}},"Router":{"types":["auto"]},"description":"Владикавказ (Дзæуджыхъæу), улица Зортова, 2","name":"Промышленный районный суд","boundedBy":[[44.67024566,43.04026124],[44.67056905,43.04060388]]},"geometry":{"type":"Point","coordinates":[44.670407,43.040433]}},{"type":"Feature","properties":{"PSearchObjectMetaData":{"id":"6099472","name":"Ленинский районный суд","nameHighlight":[[19,22]],"kind":"house","Address":{"locality":"Владикавказ (Дзæуджыхъæу)","thoroughfare":"улица Кутузова"},"address":"Владикавказ (Дзæуджыхъæу), улица Кутузова","category":"суд","categoryHighlight":[[0,3]],"internal":{"category_id":"poi-gov-court","category_name":"суд"}},"Router":{"types":["auto"]},"description":"Владикавказ (Дзæуджыхъæу), улица Кутузова","name":"Ленинский районный суд","boundedBy":[[44.69072724,43.01086635],[44.69153573,43.01145966]]},"geometry":{"type":"Point","coordinates":[44.691131,43.011163]}},{"type":"Feature","properties":{"PSearchObjectMetaData":{"id":"7738444","name":"Верховный суд РСО-Алания","nameHighlight":[[10,13]],"kind":"house","Address":{"locality":"Владикавказ (Дзæуджыхъæу)","thoroughfare":"улица Некрасова","premiseNumber":"6"},"address":"Владикавказ (Дзæуджыхъæу), улица Некрасова, 6","category":"суд","categoryHighlight":[[0,3]],"internal":{"category_id":"poi-gov-court","category_name":"суд","description":"Коллегия по гражданским делам"}},"Router":{"types":["auto"]},"description":"Владикавказ (Дзæуджыхъæу), улица Некрасова, 6","name":"Верховный суд РСО-Алания","boundedBy":[[44.67958813,43.03156288],[44.67983966,43.03172105]]},"geometry":{"type":"Point","coordinates":[44.679714,43.031642]}},{"type":"Feature","properties":{"PSearchObjectMetaData":{"id":"7738404","name":"Коллегия по гражданским делам","kind":"poi","Address":{"locality":"Владикавказ (Дзæуджыхъæу)","thoroughfare":"улица Некрасова","premiseNumber":"6"},"address":"Владикавказ (Дзæуджыхъæу), улица Некрасова, 6","category":"суд","categoryHighlight":[[0,3]],"internal":{"category_id":"poi-gov-court","category_name":"суд"}},"Router":{"types":["auto"]},"description":"Владикавказ (Дзæуджыхъæу), улица Некрасова, 6","name":"Коллегия по гражданским делам","boundedBy":[[44.67972288,43.03158265],[44.67990254,43.03171446]]},"geometry":{"type":"Point","coordinates":[44.679813,43.031649]}},{"type":"Feature","properties":{"PSearchObjectMetaData":{"id":"7738472","name":"Коллегия по уголовным делам","kind":"poi","Address":{"locality":"Владикавказ (Дзæуджыхъæу)","thoroughfare":"улица Некрасова","premiseNumber":"3"},"address":"Владикавказ (Дзæуджыхъæу), улица Некрасова, 3","category":"суд","categoryHighlight":[[0,3]],"internal":{"category_id":"poi-gov-court","category_name":"суд"}},"Router":{"types":["auto"]},"description":"Владикавказ (Дзæуджыхъæу), улица Некрасова, 3","name":"Коллегия по уголовным делам","boundedBy":[[44.67943542,43.03131246],[44.67961508,43.03144426]]},"geometry":{"type":"Point","coordinates":[44.679525,43.031378]}},{"type":"Feature","properties":{"PSearchObjectMetaData":{"id":"7738112","name":"Мировые судьи Промышленного МО","kind":"poi","Address":{"locality":"Владикавказ (Дзæуджыхъæу)","thoroughfare":"улица Цаликова/Бутаева","premiseNumber":"24"},"address":"Владикавказ (Дзæуджыхъæу), улица Цаликова/Бутаева, 24","category":"суд","categoryHighlight":[[0,3]],"internal":{"category_id":"poi-gov-court","category_name":"суд","description":"Судебные участки №№ 20-22"}},"Router":{"types":["auto"]},"description":"Владикавказ (Дзæуджыхъæу), улица Цаликова/Бутаева, 24","name":"Мировые судьи Промышленного МО","boundedBy":[[44.67375807,43.05156065],[44.67393773,43.05169241]]},"geometry":{"type":"Point","coordinates":[44.673848,43.051627]}}]},"found":23},"direct":"","Filters":[{"id":"open_now","type":"Boolean","name":"работает сейчас"}]}},"hotspots":""}